README.md
setup.py
markdown_diary.egg-info/PKG-INFO
markdown_diary.egg-info/SOURCES.txt
markdown_diary.egg-info/dependency_links.txt
markdown_diary.egg-info/entry_points.txt
markdown_diary.egg-info/top_level.txt
py_markdown_diary/Diary.py
py_markdown_diary/command_line.py