Metadata-Version: 2.1
Name: markdown-diary
Version: 0.0.1
Summary: CLI tool to generate monthly diary files in simple Markdown format
Home-page: https://github.com/skhg/markdown-diary
Author: Jack Higgins
Author-email: pypi@jackhiggins.ie
License: MIT
Keywords: diary journal markdown cli
Platform: UNKNOWN
Classifier: Development Status :: 4 - Beta
Classifier: License :: OSI Approved :: MIT License
Classifier: Programming Language :: Python :: 2.7
Classifier: Programming Language :: Python :: 3.6
